archan-3.0.0.dist-info/METADATA
archan-3.0.0.dist-info/WHEEL
archan-3.0.0.dist-info/entry_points.txt
archan-3.0.0.dist-info/licenses/LICENSE
archan/__init__.py
archan/__main__.py
archan/analysis.py
archan/cli.py
archan/config.py
archan/debug.py
archan/dsm.py
archan/enums.py
archan/errors.py
archan/logging.py
archan/plugins/__init__.py
archan/plugins/checkers.py
archan/plugins/providers.py
archan/printing.py
archan/py.typed
archan-3.0.0.dist-info/RECORD
