Metadata-Version: 2.1
Name: archan
Version: 3.0.0
Summary: Analysis of your architecture strength based on DSM data.
Author-Email: Timothée Mazzucotelli <pawamoy@pm.me>
License: ISC
Classifier: Development Status :: 4 - Beta
Classifier: Intended Audience :: Developers
Classifier: Programming Language :: Python
Classifier: Programming Language :: Python :: 3
Classifier: Programming Language :: Python :: 3 :: Only
Classifier: Programming Language :: Python :: 3.8
Classifier: Programming Language :: Python :: 3.9
Classifier: Programming Language :: Python :: 3.10
Classifier: Programming Language :: Python :: 3.11
Classifier: Programming Language :: Python :: 3.12
Classifier: Topic :: Documentation
Classifier: Topic :: Software Development
Classifier: Topic :: Utilities
Classifier: Typing :: Typed
Project-URL: Homepage, https://pawamoy.github.io/archan
Project-URL: Documentation, https://pawamoy.github.io/archan
Project-URL: Changelog, https://pawamoy.github.io/archan/changelog
Project-URL: Repository, https://github.com/pawamoy/archan
Project-URL: Issues, https://github.com/pawamoy/archan/issues
Project-URL: Discussions, https://github.com/pawamoy/archan/discussions
Project-URL: Gitter, https://gitter.im/archan/community
Project-URL: Funding, https://github.com/sponsors/pawamoy
Requires-Python: >=3.8
Requires-Dist: colorama>=0.4
Requires-Dist: pyyaml>=5.3
Requires-Dist: tap.py>=3.0
Requires-Dist: dependenpy>=3.3; extra == "dependenpy"
Provides-Extra: dependenpy
